{
  "pipeline_start_time": 1778188872.407124,
  "last_stage_completed": 7,
  "stage_results": [
    {
      "name": "Clean Output Directories",
      "exit_code": 0,
      "duration": 0.024035215377807617,
      "timestamp": "2026-05-07 14:22:31",
      "completed": true,
      "status": ""
    },
    {
      "name": "Environment Setup",
      "exit_code": 0,
      "duration": 7.422855854034424,
      "timestamp": "2026-05-07 14:22:31",
      "completed": true,
      "status": ""
    },
    {
      "name": "Project Tests",
      "exit_code": 0,
      "duration": 18.419082164764404,
      "timestamp": "2026-05-07 14:22:31",
      "completed": true,
      "status": ""
    },
    {
      "name": "Project Analysis",
      "exit_code": 0,
      "duration": 4.333897113800049,
      "timestamp": "2026-05-07 14:22:31",
      "completed": true,
      "status": ""
    },
    {
      "name": "PDF Rendering",
      "exit_code": 0,
      "duration": 47.373647928237915,
      "timestamp": "2026-05-07 14:22:31",
      "completed": true,
      "status": ""
    },
    {
      "name": "Output Validation",
      "exit_code": 0,
      "duration": 0.551459789276123,
      "timestamp": "2026-05-07 14:22:31",
      "completed": true,
      "status": ""
    },
    {
      "name": "Copy Outputs",
      "exit_code": 0,
      "duration": 0.5057737827301025,
      "timestamp": "2026-05-07 14:22:31",
      "completed": true,
      "status": ""
    }
  ],
  "total_stages": 8,
  "checkpoint_time": 1778188951.043494
}