{
  "pipeline_start_time": 1781465197.723604,
  "last_stage_completed": 8,
  "stage_results": [
    {
      "name": "Clean Output Directories",
      "exit_code": 0,
      "duration": 0.026508092880249023,
      "timestamp": "2026-06-14 12:29:05",
      "completed": true,
      "status": ""
    },
    {
      "name": "Environment Setup",
      "exit_code": 0,
      "duration": 1.3541948795318604,
      "timestamp": "2026-06-14 12:29:05",
      "completed": true,
      "status": ""
    },
    {
      "name": "Infrastructure Tests",
      "exit_code": 0,
      "duration": 9.182409048080444,
      "timestamp": "2026-06-14 12:29:05",
      "completed": true,
      "status": ""
    },
    {
      "name": "Project Tests",
      "exit_code": 0,
      "duration": 37.082831144332886,
      "timestamp": "2026-06-14 12:29:05",
      "completed": true,
      "status": ""
    },
    {
      "name": "Project Analysis",
      "exit_code": 0,
      "duration": 20.449135065078735,
      "timestamp": "2026-06-14 12:29:05",
      "completed": true,
      "status": ""
    },
    {
      "name": "PDF Rendering",
      "exit_code": 0,
      "duration": 78.01624417304993,
      "timestamp": "2026-06-14 12:29:05",
      "completed": true,
      "status": ""
    },
    {
      "name": "Output Validation",
      "exit_code": 0,
      "duration": 0.738853931427002,
      "timestamp": "2026-06-14 12:29:05",
      "completed": true,
      "status": ""
    },
    {
      "name": "Copy Outputs",
      "exit_code": 0,
      "duration": 0.5099740028381348,
      "timestamp": "2026-06-14 12:29:05",
      "completed": true,
      "status": ""
    }
  ],
  "total_stages": 10,
  "checkpoint_time": 1781465345.2395241
}